pydims/__init__.py
pydims/array_api_manipulation_functions.py
pydims/common.py
pydims/creation_functions.py
pydims/dimensioned_array.py
pydims/indexing_functions.py
pydims/py.typed
pydims/reduction_functions.py
pydims/string_units.py
pydims/testing.py
pydims/units_api_compat/__init__.py
pydims/units_api_compat/astropy.py
pydims/units_api_compat/pint.py
pydims/units_api_compat/scipp.py
pydims/units_api_compat/string_units.py
pydims/units_api_compat/units_api.py
pydims-0.7.0.dist-info/LICENSE
pydims-0.7.0.dist-info/METADATA
pydims-0.7.0.dist-info/WHEEL
pydims-0.7.0.dist-info/top_level.txt
pydims-0.7.0.dist-info/RECORD
