Metadata-Version: 2.1
Name: pydims
Version: 0.7.0
Summary: Python arrays with named dimension and physical units
Author: Scipp contributors
License: BSD 3-Clause License
Project-URL: Bug Tracker, https://github.com/pydims/pydims/issues
Project-URL: Documentation, https://pydims.github.io/pydims
Project-URL: Source, https://github.com/pydims/pydims
Classifier: Intended Audience :: Science/Research
Classifier: License :: OSI Approved :: BSD License
Classifier: Natural Language :: English
Classifier: Operating System :: OS Independent
Classifier: Programming Language :: Python :: 3
Classifier: Programming Language :: Python :: 3 :: Only
Classifier: Programming Language :: Python :: 3.12
Classifier: Topic :: Scientific/Engineering
Classifier: Typing :: Typed
Requires-Python: >=3.12
License-File: LICENSE
Requires-Dist: array-api-compat
